{
	"info": {
		"_postman_id": "69c6b33c-1f48-4f21-aa2a-6130d1016f91",
		"name": "volvo",
		"schema": "https://schema.getpostman.com/json/collection/v2.1.0/collection.json",
		"_exporter_id": "21235719",
		"_collection_link": "https://dark-water-858485.postman.co/workspace/IGEDU~a3cb930f-542d-44ee-9c0b-2443f5b0d394/collection/21235719-69c6b33c-1f48-4f21-aa2a-6130d1016f91?action=share&source=collection_link&creator=21235719"
	},
	"item": [
		{
			"name": "User",
			"item": [
				{
					"name": "Signup",
					"request": {
						"method": "POST",
						"header": [],
						"body": {
							"mode": "raw",
							"raw": "{\r\n    \"email\":\"yassentamer701@gmail.com\",\r\n    \"mobile\":\"01022884665\",\r\n    \"password\":\"yassen1214\",\r\n    \"password2\":\"yassen1214\",\r\n    \"first_name\":\"yassen\",\r\n    \"last_name\":\"tamer\"\r\n}",
							"options": {
								"raw": {
									"language": "json"
								}
							}
						},
						"url": {
							"raw": "{{local}}/api/signup",
							"host": [
								"{{local}}"
							],
							"path": [
								"api",
								"signup"
							]
						}
					},
					"response": [
						{
							"name": "Signup",
							"originalRequest": {
								"method": "POST",
								"header": [],
								"body": {
									"mode": "raw",
									"raw": "{\r\n    \"email\":\"yassentame1r702@gmail.com\",\r\n    \"mobile\":\"01022884661\",\r\n    \"password\":\"yassen1214\",\r\n    \"password2\":\"yassen1214\",\r\n    \"first_name\":\"yassen\",\r\n    \"last_name\":\"tamer\"\r\n}",
									"options": {
										"raw": {
											"language": "json"
										}
									}
								},
								"url": {
									"raw": "{{local}}/api/signup",
									"host": [
										"{{local}}"
									],
									"path": [
										"api",
										"signup"
									]
								}
							},
							"status": "Bad Request",
							"code": 400,
							"_postman_previewlanguage": "json",
							"header": [
								{
									"key": "Date",
									"value": "Sun, 03 Dec 2023 10:05:24 GMT"
								},
								{
									"key": "Server",
									"value": "WSGIServer/0.2 CPython/3.10.8"
								},
								{
									"key": "Content-Type",
									"value": "application/json"
								},
								{
									"key": "Vary",
									"value": "Accept"
								},
								{
									"key": "Allow",
									"value": "POST, OPTIONS"
								},
								{
									"key": "X-Frame-Options",
									"value": "DENY"
								},
								{
									"key": "Content-Length",
									"value": "35"
								},
								{
									"key": "X-Content-Type-Options",
									"value": "nosniff"
								},
								{
									"key": "Referrer-Policy",
									"value": "same-origin"
								}
							],
							"cookie": [],
							"body": "{\n    \"error\": \"This Mobile Used Before\"\n}"
						},
						{
							"name": "Signup",
							"originalRequest": {
								"method": "POST",
								"header": [],
								"body": {
									"mode": "raw",
									"raw": "{\r\n    \"email\":\"yassentame1r702@gmail.com\",\r\n    \"mobile\":\"01022884631\",\r\n    \"password\":\"yassen1214\",\r\n    \"password2\":\"yassen1214\",\r\n    \"first_name\":\"yassen\",\r\n    \"last_name\":\"tamer\"\r\n}",
									"options": {
										"raw": {
											"language": "json"
										}
									}
								},
								"url": {
									"raw": "{{local}}/api/signup",
									"host": [
										"{{local}}"
									],
									"path": [
										"api",
										"signup"
									]
								}
							},
							"status": "Bad Request",
							"code": 400,
							"_postman_previewlanguage": "json",
							"header": [
								{
									"key": "Date",
									"value": "Sun, 03 Dec 2023 10:06:21 GMT"
								},
								{
									"key": "Server",
									"value": "WSGIServer/0.2 CPython/3.10.8"
								},
								{
									"key": "Content-Type",
									"value": "application/json"
								},
								{
									"key": "Vary",
									"value": "Accept"
								},
								{
									"key": "Allow",
									"value": "POST, OPTIONS"
								},
								{
									"key": "X-Frame-Options",
									"value": "DENY"
								},
								{
									"key": "Content-Length",
									"value": "52"
								},
								{
									"key": "X-Content-Type-Options",
									"value": "nosniff"
								},
								{
									"key": "Referrer-Policy",
									"value": "same-origin"
								}
							],
							"cookie": [],
							"body": "{\n    \"email\": [\n        \"A user with that email already exists.\"\n    ]\n}"
						},
						{
							"name": "Signup",
							"originalRequest": {
								"method": "POST",
								"header": [],
								"body": {
									"mode": "raw",
									"raw": "{\r\n    \"email\":\"yassenw3tasme1r70s2@gmail.com\",\r\n    \"mobile\":\"0102194631\",\r\n    \"password\":\"yassen1214\",\r\n    \"password2\":\"yassen1214\",\r\n    \"first_name\":\"yassen\",\r\n    \"last_name\":\"tamer\"\r\n}",
									"options": {
										"raw": {
											"language": "json"
										}
									}
								},
								"url": {
									"raw": "https://yassentamer701.pythonanywhere.com/api/signup",
									"protocol": "https",
									"host": [
										"yassentamer701",
										"pythonanywhere",
										"com"
									],
									"path": [
										"api",
										"signup"
									]
								}
							},
							"status": "Created",
							"code": 201,
							"_postman_previewlanguage": "json",
							"header": [
								{
									"key": "Date",
									"value": "Sun, 03 Dec 2023 11:23:32 GMT"
								},
								{
									"key": "Content-Type",
									"value": "application/json"
								},
								{
									"key": "Content-Length",
									"value": "156"
								},
								{
									"key": "Connection",
									"value": "keep-alive"
								},
								{
									"key": "Vary",
									"value": "Accept"
								},
								{
									"key": "Allow",
									"value": "POST, OPTIONS"
								},
								{
									"key": "X-Frame-Options",
									"value": "DENY"
								},
								{
									"key": "X-Content-Type-Options",
									"value": "nosniff"
								},
								{
									"key": "Referrer-Policy",
									"value": "same-origin"
								},
								{
									"key": "X-Clacks-Overhead",
									"value": "GNU Terry Pratchett"
								},
								{
									"key": "Server",
									"value": "PythonAnywhere"
								}
							],
							"cookie": [],
							"body": "{\n    \"status\": true,\n    \"data\": {\n        \"email\": \"yassenw3tasme1r70s2@gmail.com\",\n        \"mobile\": \"0102194631\",\n        \"first_name\": \"yassen\",\n        \"last_name\": \"tamer\"\n    },\n    \"message\": \"تم بنجاح\"\n}"
						}
					]
				},
				{
					"name": "Submit OTP",
					"request": {
						"method": "POST",
						"header": [],
						"body": {
							"mode": "raw",
							"raw": "{\n    \"email\":\"yassentamer701@gmail.com\",\n    \"otp\":3868\n}",
							"options": {
								"raw": {
									"language": "json"
								}
							}
						},
						"url": {
							"raw": "{{local}}/api/submit_otp",
							"host": [
								"{{local}}"
							],
							"path": [
								"api",
								"submit_otp"
							]
						}
					},
					"response": []
				},
				{
					"name": "Login",
					"request": {
						"method": "POST",
						"header": [],
						"body": {
							"mode": "raw",
							"raw": "{\r\n    \"mobile\":\"01022884661\",\r\n    \"password\":\"yassen1214\"\r\n}",
							"options": {
								"raw": {
									"language": "json"
								}
							}
						},
						"url": {
							"raw": "{{local}}/api/login",
							"host": [
								"{{local}}"
							],
							"path": [
								"api",
								"login"
							]
						}
					},
					"response": [
						{
							"name": "Login",
							"originalRequest": {
								"method": "POST",
								"header": [],
								"body": {
									"mode": "raw",
									"raw": "{\r\n    \"mobile\":\"01022882666\",\r\n    \"password\":\"yassen1214\"\r\n}",
									"options": {
										"raw": {
											"language": "json"
										}
									}
								},
								"url": {
									"raw": "{{local}}/api/login",
									"host": [
										"{{local}}"
									],
									"path": [
										"api",
										"login"
									]
								}
							},
							"status": "Bad Request",
							"code": 400,
							"_postman_previewlanguage": "json",
							"header": [
								{
									"key": "Date",
									"value": "Sun, 03 Dec 2023 10:08:59 GMT"
								},
								{
									"key": "Server",
									"value": "WSGIServer/0.2 CPython/3.10.8"
								},
								{
									"key": "Content-Type",
									"value": "application/json"
								},
								{
									"key": "Vary",
									"value": "Accept"
								},
								{
									"key": "Allow",
									"value": "POST, OPTIONS"
								},
								{
									"key": "X-Frame-Options",
									"value": "DENY"
								},
								{
									"key": "Content-Length",
									"value": "33"
								},
								{
									"key": "X-Content-Type-Options",
									"value": "nosniff"
								},
								{
									"key": "Referrer-Policy",
									"value": "same-origin"
								}
							],
							"cookie": [],
							"body": "{\n    \"error\": [\n        \"user does not exist\"\n    ]\n}"
						},
						{
							"name": "Login",
							"originalRequest": {
								"method": "POST",
								"header": [],
								"body": {
									"mode": "raw",
									"raw": "{\r\n    \"mobile\":\"01022884631\",\r\n    \"password\":\"yassen1214\"\r\n}",
									"options": {
										"raw": {
											"language": "json"
										}
									}
								},
								"url": {
									"raw": "{{local}}/api/login",
									"host": [
										"{{local}}"
									],
									"path": [
										"api",
										"login"
									]
								}
							},
							"status": "OK",
							"code": 200,
							"_postman_previewlanguage": "json",
							"header": [
								{
									"key": "Date",
									"value": "Sun, 03 Dec 2023 10:09:37 GMT"
								},
								{
									"key": "Server",
									"value": "WSGIServer/0.2 CPython/3.10.8"
								},
								{
									"key": "Content-Type",
									"value": "application/json"
								},
								{
									"key": "Vary",
									"value": "Accept"
								},
								{
									"key": "Allow",
									"value": "POST, OPTIONS"
								},
								{
									"key": "X-Frame-Options",
									"value": "DENY"
								},
								{
									"key": "Content-Length",
									"value": "724"
								},
								{
									"key": "X-Content-Type-Options",
									"value": "nosniff"
								},
								{
									"key": "Referrer-Policy",
									"value": "same-origin"
								}
							],
							"cookie": [],
							"body": "{\n    \"refresh\": \"eyJ0eXAiOiJKV1QiLCJhbGciOiJIUzI1NiJ9.eyJ0b2tlbl90eXBlIjoicmVmcmVzaCIsImV4cCI6MTcwOTM3NDE3NywianRpIjoiNWQ1ZThmOTFjOTlmNDNiZWE1YmE3OGUyNDFkZjFmMTMiLCJ1c2VyX2lkIjoiNyIsImZpcnN0X25hbWUiOiJ5YXNzZW4iLCJsYXN0X25hbWUiOiJ0YW1lciJ9.xAM1psvtPE1lCH_Qgw1Q2yNalm7LZ9uiMZ6FD9AxNVc\",\n    \"access\": \"eyJ0eXAiOiJKV1QiLCJhbGciOiJIUzI1NiJ9.eyJ0b2tlbl90eXBlIjoiYWNjZXNzIiwiZXhwIjoxNzA5Mzc0MTc3LCJqdGkiOiIxZThiZTVkYTYxZTg0MmY0YmNiNjRkMjFkMTUzYmU5YyIsInVzZXJfaWQiOiI3IiwiZmlyc3RfbmFtZSI6Inlhc3NlbiIsImxhc3RfbmFtZSI6InRhbWVyIn0.lCtgLJCG_la5DYdJXckX4H2zy5PswlqHa-1wDuYZSjE\",\n    \"user_data\": {\n        \"id\": 7,\n        \"first_name\": \"yassen\",\n        \"last_name\": \"tamer\",\n        \"username\": null,\n        \"mobile\": \"01022884631\",\n        \"email\": \"yassentame1r70s2@gmail.com\",\n        \"avatar\": null,\n        \"mypoints\": null\n    }\n}"
						}
					]
				},
				{
					"name": "ِAdd User Car",
					"request": {
						"auth": {
							"type": "bearer",
							"bearer": [
								{
									"key": "token",
									"value": "eyJ0eXAiOiJKV1QiLCJhbGciOiJIUzI1NiJ9.eyJ0b2tlbl90eXBlIjoiYWNjZXNzIiwiZXhwIjoxNzA4ODcxMTkzLCJqdGkiOiJiNGEzMWNhYTQxNzM0NjY5ODVhNGU0OTRlYWUyZDQ1YSIsInVzZXJfaWQiOiIzIiwiZmlyc3RfbmFtZSI6Inlhc3NlbiIsImxhc3RfbmFtZSI6InRhbWVyIn0.ls60Lt5ZHM_t7ngW1syX3eY5hxXFWXC1JFWFjyrqM8s",
									"type": "string"
								}
							]
						},
						"method": "POST",
						"header": [],
						"body": {
							"mode": "raw",
							"raw": "{\r\n    \"car_model\":1,\r\n    \"model_year\":2018,\r\n    \"chassis_number\":\"456787654\",\r\n    \"plate_number\":\"asgfjk\",\r\n    \"car_document_front\":\"\",\r\n    \"car_document_back\":\"\"\r\n}",
							"options": {
								"raw": {
									"language": "json"
								}
							}
						},
						"url": {
							"raw": "{{local}}/api/add_user_car",
							"host": [
								"{{local}}"
							],
							"path": [
								"api",
								"add_user_car"
							]
						}
					},
					"response": [
						{
							"name": "ِAdd User Car",
							"originalRequest": {
								"method": "POST",
								"header": [],
								"body": {
									"mode": "raw",
									"raw": "{\r\n    \"car_model\":1,\r\n    \"model_year\":2018,\r\n    \"chassis_number\":\"456787654\",\r\n    \"plate_number\":\"asgfjk\",\r\n    \"car_document_front\":\"\",\r\n    \"car_document_back\":\"\"\r\n}",
									"options": {
										"raw": {
											"language": "json"
										}
									}
								},
								"url": {
									"raw": "{{local}}/api/add_user_car",
									"host": [
										"{{local}}"
									],
									"path": [
										"api",
										"add_user_car"
									]
								}
							},
							"status": "Created",
							"code": 201,
							"_postman_previewlanguage": "json",
							"header": [
								{
									"key": "Date",
									"value": "Sun, 03 Dec 2023 10:09:51 GMT"
								},
								{
									"key": "Server",
									"value": "WSGIServer/0.2 CPython/3.10.8"
								},
								{
									"key": "Content-Type",
									"value": "application/json"
								},
								{
									"key": "Vary",
									"value": "Accept"
								},
								{
									"key": "Allow",
									"value": "POST, OPTIONS"
								},
								{
									"key": "X-Frame-Options",
									"value": "DENY"
								},
								{
									"key": "Content-Length",
									"value": "290"
								},
								{
									"key": "X-Content-Type-Options",
									"value": "nosniff"
								},
								{
									"key": "Referrer-Policy",
									"value": "same-origin"
								}
							],
							"cookie": [],
							"body": "{\n    \"status\": true,\n    \"data\": {\n        \"id\": 2,\n        \"car_document_front\": null,\n        \"car_document_back\": null,\n        \"created_at\": \"2023-12-03T10:09:51.138631Z\",\n        \"updated_at\": \"2023-12-03T10:09:51.138631Z\",\n        \"model_year\": 2018,\n        \"chassis_number\": \"456787654\",\n        \"plate_number\": \"asgfjk\",\n        \"user\": 3,\n        \"car_model\": 1\n    },\n    \"message\": \"تم بنجاح\"\n}"
						}
					]
				},
				{
					"name": "ListMyHistory",
					"request": {
						"auth": {
							"type": "bearer",
							"bearer": [
								{
									"key": "token",
									"value": "eyJ0eXAiOiJKV1QiLCJhbGciOiJIUzI1NiJ9.eyJ0b2tlbl90eXBlIjoiYWNjZXNzIiwiZXhwIjoxNzA4ODcxMTkzLCJqdGkiOiJiNGEzMWNhYTQxNzM0NjY5ODVhNGU0OTRlYWUyZDQ1YSIsInVzZXJfaWQiOiIzIiwiZmlyc3RfbmFtZSI6Inlhc3NlbiIsImxhc3RfbmFtZSI6InRhbWVyIn0.ls60Lt5ZHM_t7ngW1syX3eY5hxXFWXC1JFWFjyrqM8s",
									"type": "string"
								}
							]
						},
						"method": "GET",
						"header": [],
						"url": {
							"raw": "{{local}}/api/my_history",
							"host": [
								"{{local}}"
							],
							"path": [
								"api",
								"my_history"
							]
						}
					},
					"response": [
						{
							"name": "ListMyHistory",
							"originalRequest": {
								"method": "GET",
								"header": [],
								"url": {
									"raw": "{{local}}/api/my_history",
									"host": [
										"{{local}}"
									],
									"path": [
										"api",
										"my_history"
									]
								}
							},
							"status": "OK",
							"code": 200,
							"_postman_previewlanguage": "json",
							"header": [
								{
									"key": "Date",
									"value": "Sun, 03 Dec 2023 10:10:03 GMT"
								},
								{
									"key": "Server",
									"value": "WSGIServer/0.2 CPython/3.10.8"
								},
								{
									"key": "Content-Type",
									"value": "application/json"
								},
								{
									"key": "Vary",
									"value": "Accept"
								},
								{
									"key": "Allow",
									"value": "GET, HEAD, OPTIONS"
								},
								{
									"key": "X-Frame-Options",
									"value": "DENY"
								},
								{
									"key": "Content-Length",
									"value": "426"
								},
								{
									"key": "X-Content-Type-Options",
									"value": "nosniff"
								},
								{
									"key": "Referrer-Policy",
									"value": "same-origin"
								}
							],
							"cookie": [],
							"body": "{\n    \"status\": true,\n    \"data\": [\n        {\n            \"id\": 1,\n            \"service\": [\n                {\n                    \"id\": 1,\n                    \"created_at\": \"2023-11-27T19:12:12.617751Z\",\n                    \"updated_at\": \"2023-11-27T19:12:12.617751Z\",\n                    \"price\": 1500,\n                    \"min_price\": 1000,\n                    \"max_price\": 1500,\n                    \"name\": \"test service\",\n                    \"icons\": null,\n                    \"points\": 100\n                }\n            ],\n            \"created_at\": \"2023-11-27T19:30:28.738471Z\",\n            \"updated_at\": \"2023-11-27T19:36:55.651460Z\",\n            \"price\": 1500,\n            \"date\": \"2023-11-27T19:12:16Z\",\n            \"file\": null,\n            \"user\": 3,\n            \"points\": 100\n        }\n    ],\n    \"message\": \"تم بنجاح\"\n}"
						}
					]
				},
				{
					"name": "ListUserCars",
					"request": {
						"auth": {
							"type": "bearer",
							"bearer": [
								{
									"key": "token",
									"value": "eyJ0eXAiOiJKV1QiLCJhbGciOiJIUzI1NiJ9.eyJ0b2tlbl90eXBlIjoiYWNjZXNzIiwiZXhwIjoxNzA4ODcxMTkzLCJqdGkiOiJiNGEzMWNhYTQxNzM0NjY5ODVhNGU0OTRlYWUyZDQ1YSIsInVzZXJfaWQiOiIzIiwiZmlyc3RfbmFtZSI6Inlhc3NlbiIsImxhc3RfbmFtZSI6InRhbWVyIn0.ls60Lt5ZHM_t7ngW1syX3eY5hxXFWXC1JFWFjyrqM8s",
									"type": "string"
								}
							]
						},
						"method": "GET",
						"header": [],
						"url": {
							"raw": "{{local}}/api/list_user_cars",
							"host": [
								"{{local}}"
							],
							"path": [
								"api",
								"list_user_cars"
							]
						}
					},
					"response": [
						{
							"name": "ListUserCars",
							"originalRequest": {
								"method": "GET",
								"header": [],
								"url": {
									"raw": "{{local}}/api/list_user_cars",
									"host": [
										"{{local}}"
									],
									"path": [
										"api",
										"list_user_cars"
									]
								}
							},
							"status": "Unauthorized",
							"code": 401,
							"_postman_previewlanguage": "json",
							"header": [
								{
									"key": "Date",
									"value": "Sun, 03 Dec 2023 10:10:55 GMT"
								},
								{
									"key": "Server",
									"value": "WSGIServer/0.2 CPython/3.10.8"
								},
								{
									"key": "Content-Type",
									"value": "application/json"
								},
								{
									"key": "WWW-Authenticate",
									"value": "Bearer realm=\"api\""
								},
								{
									"key": "Vary",
									"value": "Accept"
								},
								{
									"key": "Allow",
									"value": "GET, HEAD, OPTIONS"
								},
								{
									"key": "X-Frame-Options",
									"value": "DENY"
								},
								{
									"key": "Content-Length",
									"value": "183"
								},
								{
									"key": "X-Content-Type-Options",
									"value": "nosniff"
								},
								{
									"key": "Referrer-Policy",
									"value": "same-origin"
								}
							],
							"cookie": [],
							"body": "{\n    \"detail\": \"Given token not valid for any token type\",\n    \"code\": \"token_not_valid\",\n    \"messages\": [\n        {\n            \"token_class\": \"AccessToken\",\n            \"token_type\": \"access\",\n            \"message\": \"Token is invalid or expired\"\n        }\n    ]\n}"
						},
						{
							"name": "ListUserCars",
							"originalRequest": {
								"method": "GET",
								"header": [],
								"url": {
									"raw": "{{local}}/api/list_user_cars",
									"host": [
										"{{local}}"
									],
									"path": [
										"api",
										"list_user_cars"
									]
								}
							},
							"status": "OK",
							"code": 200,
							"_postman_previewlanguage": "json",
							"header": [
								{
									"key": "Date",
									"value": "Sun, 03 Dec 2023 10:11:16 GMT"
								},
								{
									"key": "Server",
									"value": "WSGIServer/0.2 CPython/3.10.8"
								},
								{
									"key": "Content-Type",
									"value": "application/json"
								},
								{
									"key": "Vary",
									"value": "Accept"
								},
								{
									"key": "Allow",
									"value": "GET, HEAD, OPTIONS"
								},
								{
									"key": "X-Frame-Options",
									"value": "DENY"
								},
								{
									"key": "Content-Length",
									"value": "532"
								},
								{
									"key": "X-Content-Type-Options",
									"value": "nosniff"
								},
								{
									"key": "Referrer-Policy",
									"value": "same-origin"
								}
							],
							"cookie": [],
							"body": "{\n    \"status\": true,\n    \"data\": [\n        {\n            \"id\": 2,\n            \"created_at\": \"2023-12-03T10:09:51.138631Z\",\n            \"updated_at\": \"2023-12-03T10:09:51.138631Z\",\n            \"model_year\": 2018,\n            \"chassis_number\": \"456787654\",\n            \"plate_number\": \"asgfjk\",\n            \"car_document_front\": null,\n            \"car_document_back\": null,\n            \"user\": 3,\n            \"car_model\": 1\n        },\n        {\n            \"id\": 1,\n            \"created_at\": \"2023-11-27T14:27:50.290456Z\",\n            \"updated_at\": \"2023-11-27T14:27:50.290456Z\",\n            \"model_year\": 2018,\n            \"chassis_number\": \"456787654\",\n            \"plate_number\": \"asgfjk\",\n            \"car_document_front\": null,\n            \"car_document_back\": null,\n            \"user\": 3,\n            \"car_model\": 1\n        }\n    ],\n    \"message\": \"تم بنجاح\"\n}"
						}
					]
				},
				{
					"name": "Profile",
					"request": {
						"auth": {
							"type": "bearer",
							"bearer": [
								{
									"key": "token",
									"value": "eyJ0eXAiOiJKV1QiLCJhbGciOiJIUzI1NiJ9.eyJ0b2tlbl90eXBlIjoiYWNjZXNzIiwiZXhwIjoxNzA4ODcxMTkzLCJqdGkiOiJiNGEzMWNhYTQxNzM0NjY5ODVhNGU0OTRlYWUyZDQ1YSIsInVzZXJfaWQiOiIzIiwiZmlyc3RfbmFtZSI6Inlhc3NlbiIsImxhc3RfbmFtZSI6InRhbWVyIn0.ls60Lt5ZHM_t7ngW1syX3eY5hxXFWXC1JFWFjyrqM8s",
									"type": "string"
								}
							]
						},
						"method": "GET",
						"header": [],
						"url": {
							"raw": "{{local}}/api/profile",
							"host": [
								"{{local}}"
							],
							"path": [
								"api",
								"profile"
							]
						}
					},
					"response": [
						{
							"name": "Profile",
							"originalRequest": {
								"method": "GET",
								"header": [],
								"url": {
									"raw": "{{local}}/api/profile",
									"host": [
										"{{local}}"
									],
									"path": [
										"api",
										"profile"
									]
								}
							},
							"status": "OK",
							"code": 200,
							"_postman_previewlanguage": "json",
							"header": [
								{
									"key": "Date",
									"value": "Sun, 03 Dec 2023 10:12:01 GMT"
								},
								{
									"key": "Server",
									"value": "WSGIServer/0.2 CPython/3.10.8"
								},
								{
									"key": "Content-Type",
									"value": "application/json"
								},
								{
									"key": "Vary",
									"value": "Accept"
								},
								{
									"key": "Allow",
									"value": "GET, HEAD, OPTIONS"
								},
								{
									"key": "X-Frame-Options",
									"value": "DENY"
								},
								{
									"key": "Content-Length",
									"value": "204"
								},
								{
									"key": "X-Content-Type-Options",
									"value": "nosniff"
								},
								{
									"key": "Referrer-Policy",
									"value": "same-origin"
								}
							],
							"cookie": [],
							"body": "{\n    \"status\": true,\n    \"data\": {\n        \"id\": 3,\n        \"first_name\": \"yassen\",\n        \"last_name\": \"tamer\",\n        \"username\": null,\n        \"mobile\": \"01022882665\",\n        \"email\": \"yassentamer705@gmail.com\",\n        \"avatar\": null,\n        \"mypoints\": 100\n    },\n    \"message\": \"تم بنجاح\"\n}"
						}
					]
				},
				{
					"name": "Update Profile",
					"request": {
						"auth": {
							"type": "bearer",
							"bearer": [
								{
									"key": "token",
									"value": "eyJ0eXAiOiJKV1QiLCJhbGciOiJIUzI1NiJ9.eyJ0b2tlbl90eXBlIjoiYWNjZXNzIiwiZXhwIjoxNzA4ODcxMTkzLCJqdGkiOiJiNGEzMWNhYTQxNzM0NjY5ODVhNGU0OTRlYWUyZDQ1YSIsInVzZXJfaWQiOiIzIiwiZmlyc3RfbmFtZSI6Inlhc3NlbiIsImxhc3RfbmFtZSI6InRhbWVyIn0.ls60Lt5ZHM_t7ngW1syX3eY5hxXFWXC1JFWFjyrqM8s",
									"type": "string"
								}
							]
						},
						"method": "POST",
						"header": [],
						"body": {
							"mode": "raw",
							"raw": "{\r\n    \"email\":\"yassentamer705@gmail.com\",\r\n    \"mobile\":\"01022882665\",\r\n    \"first_name\":\"yassen\",\r\n    \"last_name\":\"tamer\",\r\n    \"avatar\":\"\"\r\n}",
							"options": {
								"raw": {
									"language": "json"
								}
							}
						},
						"url": {
							"raw": "{{local}}/api/update_profile",
							"host": [
								"{{local}}"
							],
							"path": [
								"api",
								"update_profile"
							]
						}
					},
					"response": [
						{
							"name": "Update Profile",
							"originalRequest": {
								"method": "POST",
								"header": [],
								"body": {
									"mode": "raw",
									"raw": "{\r\n    \"email\":\"yassentamer705@gmail.com\",\r\n    \"mobile\":\"01032882665\",\r\n    \"first_name\":\"yassen\",\r\n    \"last_name\":\"tamer\",\r\n    \"avatar\":\"\"\r\n}",
									"options": {
										"raw": {
											"language": "json"
										}
									}
								},
								"url": {
									"raw": "{{local}}/api/update_profile",
									"host": [
										"{{local}}"
									],
									"path": [
										"api",
										"update_profile"
									]
								}
							},
							"status": "OK",
							"code": 200,
							"_postman_previewlanguage": "json",
							"header": [
								{
									"key": "Date",
									"value": "Sun, 03 Dec 2023 10:12:40 GMT"
								},
								{
									"key": "Server",
									"value": "WSGIServer/0.2 CPython/3.10.8"
								},
								{
									"key": "Content-Type",
									"value": "application/json"
								},
								{
									"key": "Vary",
									"value": "Accept"
								},
								{
									"key": "Allow",
									"value": "POST, OPTIONS"
								},
								{
									"key": "X-Frame-Options",
									"value": "DENY"
								},
								{
									"key": "Content-Length",
									"value": "204"
								},
								{
									"key": "X-Content-Type-Options",
									"value": "nosniff"
								},
								{
									"key": "Referrer-Policy",
									"value": "same-origin"
								}
							],
							"cookie": [],
							"body": "{\n    \"status\": true,\n    \"data\": {\n        \"id\": 3,\n        \"first_name\": \"yassen\",\n        \"last_name\": \"tamer\",\n        \"username\": null,\n        \"email\": \"yassentamer705@gmail.com\",\n        \"mobile\": \"01032882665\",\n        \"avatar\": null,\n        \"mypoints\": 100\n    },\n    \"message\": \"تم بنجاح\"\n}"
						},
						{
							"name": "Update Profile",
							"originalRequest": {
								"method": "POST",
								"header": [],
								"body": {
									"mode": "raw",
									"raw": "{\r\n    \"email\":\"yassentamer705@gmail.com\",\r\n    \"mobile\":\"01032882665\",\r\n    \"first_name\":\"yassen\",\r\n    \"last_name\":\"tamer\",\r\n    \"avatar\":\"\"\r\n}",
									"options": {
										"raw": {
											"language": "json"
										}
									}
								},
								"url": {
									"raw": "{{local}}/api/update_profile",
									"host": [
										"{{local}}"
									],
									"path": [
										"api",
										"update_profile"
									]
								}
							},
							"status": "Bad Request",
							"code": 400,
							"_postman_previewlanguage": "json",
							"header": [
								{
									"key": "Date",
									"value": "Sun, 03 Dec 2023 10:12:51 GMT"
								},
								{
									"key": "Server",
									"value": "WSGIServer/0.2 CPython/3.10.8"
								},
								{
									"key": "Content-Type",
									"value": "application/json"
								},
								{
									"key": "Vary",
									"value": "Accept"
								},
								{
									"key": "Allow",
									"value": "POST, OPTIONS"
								},
								{
									"key": "X-Frame-Options",
									"value": "DENY"
								},
								{
									"key": "Content-Length",
									"value": "98"
								},
								{
									"key": "X-Content-Type-Options",
									"value": "nosniff"
								},
								{
									"key": "Referrer-Policy",
									"value": "same-origin"
								}
							],
							"cookie": [],
							"body": "{\n    \"status\": false,\n    \"data\": \"\",\n    \"message\": \"يوجد حساب مسجل برقم الموبايل هذا\"\n}"
						}
					]
				},
				{
					"name": "Change Password",
					"request": {
						"auth": {
							"type": "bearer",
							"bearer": [
								{
									"key": "token",
									"value": "eyJ0eXAiOiJKV1QiLCJhbGciOiJIUzI1NiJ9.eyJ0b2tlbl90eXBlIjoiYWNjZXNzIiwiZXhwIjoxNzA4ODcxMTkzLCJqdGkiOiJiNGEzMWNhYTQxNzM0NjY5ODVhNGU0OTRlYWUyZDQ1YSIsInVzZXJfaWQiOiIzIiwiZmlyc3RfbmFtZSI6Inlhc3NlbiIsImxhc3RfbmFtZSI6InRhbWVyIn0.ls60Lt5ZHM_t7ngW1syX3eY5hxXFWXC1JFWFjyrqM8s",
									"type": "string"
								}
							]
						},
						"method": "POST",
						"header": [],
						"body": {
							"mode": "raw",
							"raw": "{\r\n    \"old_password\":\"yassen1214\",\r\n    \"new_password\":\"yassen@1214\",\r\n    \"conf_password\":\"yassen@1214\"\r\n}",
							"options": {
								"raw": {
									"language": "json"
								}
							}
						},
						"url": {
							"raw": "{{local}}/api/change_password",
							"host": [
								"{{local}}"
							],
							"path": [
								"api",
								"change_password"
							]
						}
					},
					"response": [
						{
							"name": "Change Password",
							"originalRequest": {
								"method": "POST",
								"header": [],
								"body": {
									"mode": "raw",
									"raw": "{\r\n    \"old_password\":\"yassen1214\",\r\n    \"new_password\":\"yassen@1214\",\r\n    \"conf_password\":\"yassen@1214\"\r\n}",
									"options": {
										"raw": {
											"language": "json"
										}
									}
								},
								"url": {
									"raw": "{{local}}/api/change_password",
									"host": [
										"{{local}}"
									],
									"path": [
										"api",
										"change_password"
									]
								}
							},
							"status": "OK",
							"code": 200,
							"_postman_previewlanguage": "json",
							"header": [
								{
									"key": "Date",
									"value": "Sun, 03 Dec 2023 10:13:07 GMT"
								},
								{
									"key": "Server",
									"value": "WSGIServer/0.2 CPython/3.10.8"
								},
								{
									"key": "Content-Type",
									"value": "application/json"
								},
								{
									"key": "Vary",
									"value": "Accept"
								},
								{
									"key": "Allow",
									"value": "POST, OPTIONS"
								},
								{
									"key": "X-Frame-Options",
									"value": "DENY"
								},
								{
									"key": "Content-Length",
									"value": "17"
								},
								{
									"key": "X-Content-Type-Options",
									"value": "nosniff"
								},
								{
									"key": "Referrer-Policy",
									"value": "same-origin"
								}
							],
							"cookie": [],
							"body": "{\n    \"error\": \"error\"\n}"
						},
						{
							"name": "Change Password",
							"originalRequest": {
								"method": "POST",
								"header": [],
								"body": {
									"mode": "raw",
									"raw": "{\r\n    \"old_password\":\"yassen@1214\",\r\n    \"new_password\":\"yassen1214\",\r\n    \"conf_password\":\"yassen1214\"\r\n}",
									"options": {
										"raw": {
											"language": "json"
										}
									}
								},
								"url": {
									"raw": "{{local}}/api/change_password",
									"host": [
										"{{local}}"
									],
									"path": [
										"api",
										"change_password"
									]
								}
							},
							"status": "OK",
							"code": 200,
							"_postman_previewlanguage": "json",
							"header": [
								{
									"key": "Date",
									"value": "Sun, 03 Dec 2023 10:13:29 GMT"
								},
								{
									"key": "Server",
									"value": "WSGIServer/0.2 CPython/3.10.8"
								},
								{
									"key": "Content-Type",
									"value": "application/json"
								},
								{
									"key": "Vary",
									"value": "Accept, Cookie"
								},
								{
									"key": "Allow",
									"value": "POST, OPTIONS"
								},
								{
									"key": "X-Frame-Options",
									"value": "DENY"
								},
								{
									"key": "Content-Length",
									"value": "85"
								},
								{
									"key": "X-Content-Type-Options",
									"value": "nosniff"
								},
								{
									"key": "Referrer-Policy",
									"value": "same-origin"
								},
								{
									"key": "Set-Cookie",
									"value": "sessionid=bpekwudkfs3pie5syy4kpj6wu4uyhr37; expires=Sun, 17 Dec 2023 10:13:29 GMT; HttpOnly; Max-Age=1209600; Path=/; SameSite=Lax"
								}
							],
							"cookie": [],
							"body": "{\n    \"status\": true,\n    \"data\": \"You Have Changed Your Password!!\",\n    \"message\": \"تم بنجاح\"\n}"
						}
					]
				}
			]
		},
		{
			"name": "Booking",
			"item": [
				{
					"name": "Book Used Cars",
					"request": {
						"auth": {
							"type": "bearer",
							"bearer": [
								{
									"key": "token",
									"value": "eyJ0eXAiOiJKV1QiLCJhbGciOiJIUzI1NiJ9.eyJ0b2tlbl90eXBlIjoiYWNjZXNzIiwiZXhwIjoxNzA4ODcxMTkzLCJqdGkiOiJiNGEzMWNhYTQxNzM0NjY5ODVhNGU0OTRlYWUyZDQ1YSIsInVzZXJfaWQiOiIzIiwiZmlyc3RfbmFtZSI6Inlhc3NlbiIsImxhc3RfbmFtZSI6InRhbWVyIn0.ls60Lt5ZHM_t7ngW1syX3eY5hxXFWXC1JFWFjyrqM8s",
									"type": "string"
								}
							]
						},
						"method": "POST",
						"header": [],
						"body": {
							"mode": "raw",
							"raw": "{\r\n    \"used_cars\":1,\r\n    \"date\":\"2023-12-02\"\r\n}",
							"options": {
								"raw": {
									"language": "json"
								}
							}
						},
						"url": {
							"raw": "{{local}}/api/book_used_cars",
							"host": [
								"{{local}}"
							],
							"path": [
								"api",
								"book_used_cars"
							]
						}
					},
					"response": [
						{
							"name": "Book Used Cars",
							"originalRequest": {
								"method": "POST",
								"header": [],
								"body": {
									"mode": "raw",
									"raw": "{\r\n    \"used_cars\":1,\r\n    \"date\":\"2023-12-02\"\r\n}",
									"options": {
										"raw": {
											"language": "json"
										}
									}
								},
								"url": {
									"raw": "{{local}}/api/book_used_cars",
									"host": [
										"{{local}}"
									],
									"path": [
										"api",
										"book_used_cars"
									]
								}
							},
							"status": "Created",
							"code": 201,
							"_postman_previewlanguage": "json",
							"header": [
								{
									"key": "Date",
									"value": "Sun, 03 Dec 2023 10:04:05 GMT"
								},
								{
									"key": "Server",
									"value": "WSGIServer/0.2 CPython/3.10.8"
								},
								{
									"key": "Content-Type",
									"value": "application/json"
								},
								{
									"key": "Vary",
									"value": "Accept"
								},
								{
									"key": "Allow",
									"value": "POST, OPTIONS"
								},
								{
									"key": "X-Frame-Options",
									"value": "DENY"
								},
								{
									"key": "Content-Length",
									"value": "188"
								},
								{
									"key": "X-Content-Type-Options",
									"value": "nosniff"
								},
								{
									"key": "Referrer-Policy",
									"value": "same-origin"
								}
							],
							"cookie": [],
							"body": "{\n    \"status\": true,\n    \"data\": {\n        \"id\": 2,\n        \"created_at\": \"2023-12-03T10:04:05.271873Z\",\n        \"updated_at\": \"2023-12-03T10:04:05.271873Z\",\n        \"date\": \"2023-12-02\",\n        \"user\": 3,\n        \"used_cars\": 1\n    },\n    \"message\": \"تم بنجاح\"\n}"
						}
					]
				},
				{
					"name": "Book A Service",
					"request": {
						"auth": {
							"type": "bearer",
							"bearer": [
								{
									"key": "token",
									"value": "eyJ0eXAiOiJKV1QiLCJhbGciOiJIUzI1NiJ9.eyJ0b2tlbl90eXBlIjoiYWNjZXNzIiwiZXhwIjoxNzA4ODcxMTkzLCJqdGkiOiJiNGEzMWNhYTQxNzM0NjY5ODVhNGU0OTRlYWUyZDQ1YSIsInVzZXJfaWQiOiIzIiwiZmlyc3RfbmFtZSI6Inlhc3NlbiIsImxhc3RfbmFtZSI6InRhbWVyIn0.ls60Lt5ZHM_t7ngW1syX3eY5hxXFWXC1JFWFjyrqM8s",
									"type": "string"
								}
							]
						},
						"method": "POST",
						"header": [],
						"body": {
							"mode": "raw",
							"raw": "{\r\n    \"services\":[1],\r\n    \"time_id\":1,\r\n    \"user_car\":1,\r\n    \"branch_id\":2,\r\n    \"date\":\"2023-12-10\"\r\n}",
							"options": {
								"raw": {
									"language": "json"
								}
							}
						},
						"url": {
							"raw": "{{local}}/api/book_a_service",
							"host": [
								"{{local}}"
							],
							"path": [
								"api",
								"book_a_service"
							]
						}
					},
					"response": [
						{
							"name": "Book A Service",
							"originalRequest": {
								"method": "POST",
								"header": [],
								"body": {
									"mode": "raw",
									"raw": "{\r\n    \"services\":[1],\r\n    \"time_id\":1,\r\n    \"user_car\":1,\r\n    \"branch_id\":2,\r\n    \"date\":\"2023-12-10\"\r\n}",
									"options": {
										"raw": {
											"language": "json"
										}
									}
								},
								"url": {
									"raw": "{{local}}/api/book_a_service",
									"host": [
										"{{local}}"
									],
									"path": [
										"api",
										"book_a_service"
									]
								}
							},
							"status": "OK",
							"code": 200,
							"_postman_previewlanguage": "json",
							"header": [
								{
									"key": "Date",
									"value": "Sun, 03 Dec 2023 10:18:21 GMT"
								},
								{
									"key": "Server",
									"value": "WSGIServer/0.2 CPython/3.10.8"
								},
								{
									"key": "Content-Type",
									"value": "application/json"
								},
								{
									"key": "Vary",
									"value": "Accept"
								},
								{
									"key": "Allow",
									"value": "POST, OPTIONS"
								},
								{
									"key": "X-Frame-Options",
									"value": "DENY"
								},
								{
									"key": "Content-Length",
									"value": "230"
								},
								{
									"key": "X-Content-Type-Options",
									"value": "nosniff"
								},
								{
									"key": "Referrer-Policy",
									"value": "same-origin"
								}
							],
							"cookie": [],
							"body": "{\n    \"status\": true,\n    \"data\": {\n        \"id\": 5,\n        \"created_at\": \"2023-12-03T10:18:21.725796Z\",\n        \"updated_at\": \"2023-12-03T10:18:21.738761Z\",\n        \"date\": \"2023-12-10\",\n        \"status\": false,\n        \"user_car\": 1,\n        \"branch\": 2,\n        \"time\": null,\n        \"service\": [\n            1\n        ]\n    },\n    \"message\": \"تم بنجاح\"\n}"
						}
					]
				},
				{
					"name": "Book Accessories",
					"request": {
						"auth": {
							"type": "bearer",
							"bearer": [
								{
									"key": "token",
									"value": "eyJ0eXAiOiJKV1QiLCJhbGciOiJIUzI1NiJ9.eyJ0b2tlbl90eXBlIjoiYWNjZXNzIiwiZXhwIjoxNzA4ODcxMTkzLCJqdGkiOiJiNGEzMWNhYTQxNzM0NjY5ODVhNGU0OTRlYWUyZDQ1YSIsInVzZXJfaWQiOiIzIiwiZmlyc3RfbmFtZSI6Inlhc3NlbiIsImxhc3RfbmFtZSI6InRhbWVyIn0.ls60Lt5ZHM_t7ngW1syX3eY5hxXFWXC1JFWFjyrqM8s",
									"type": "string"
								}
							]
						},
						"method": "POST",
						"header": [],
						"body": {
							"mode": "raw",
							"raw": "{\r\n    \"accessories\":1,\r\n    \"branch\":1,\r\n    \"date\":\"2023-12-02\"\r\n}",
							"options": {
								"raw": {
									"language": "json"
								}
							}
						},
						"url": {
							"raw": "{{local}}/api/book_accessories",
							"host": [
								"{{local}}"
							],
							"path": [
								"api",
								"book_accessories"
							]
						}
					},
					"response": [
						{
							"name": "Book Accessories",
							"originalRequest": {
								"method": "POST",
								"header": [],
								"body": {
									"mode": "raw",
									"raw": "{\r\n    \"accessories\":1,\r\n    \"branch\":1,\r\n    \"date\":\"2023-12-02\"\r\n}",
									"options": {
										"raw": {
											"language": "json"
										}
									}
								},
								"url": {
									"raw": "{{local}}/api/book_accessories",
									"host": [
										"{{local}}"
									],
									"path": [
										"api",
										"book_accessories"
									]
								}
							},
							"status": "Created",
							"code": 201,
							"_postman_previewlanguage": "json",
							"header": [
								{
									"key": "Date",
									"value": "Sun, 03 Dec 2023 10:04:23 GMT"
								},
								{
									"key": "Server",
									"value": "WSGIServer/0.2 CPython/3.10.8"
								},
								{
									"key": "Content-Type",
									"value": "application/json"
								},
								{
									"key": "Vary",
									"value": "Accept"
								},
								{
									"key": "Allow",
									"value": "POST, OPTIONS"
								},
								{
									"key": "X-Frame-Options",
									"value": "DENY"
								},
								{
									"key": "Content-Length",
									"value": "201"
								},
								{
									"key": "X-Content-Type-Options",
									"value": "nosniff"
								},
								{
									"key": "Referrer-Policy",
									"value": "same-origin"
								}
							],
							"cookie": [],
							"body": "{\n    \"status\": true,\n    \"data\": {\n        \"id\": 2,\n        \"created_at\": \"2023-12-03T10:04:23.310811Z\",\n        \"updated_at\": \"2023-12-03T10:04:23.310811Z\",\n        \"date\": \"2023-12-02\",\n        \"user\": 3,\n        \"accessories\": 1,\n        \"branch\": 1\n    },\n    \"message\": \"تم بنجاح\"\n}"
						}
					]
				},
				{
					"name": "List Slots",
					"request": {
						"auth": {
							"type": "bearer",
							"bearer": [
								{
									"key": "token",
									"value": "eyJ0eXAiOiJKV1QiLCJhbGciOiJIUzI1NiJ9.eyJ0b2tlbl90eXBlIjoiYWNjZXNzIiwiZXhwIjoxNzA4ODcxMTkzLCJqdGkiOiJiNGEzMWNhYTQxNzM0NjY5ODVhNGU0OTRlYWUyZDQ1YSIsInVzZXJfaWQiOiIzIiwiZmlyc3RfbmFtZSI6Inlhc3NlbiIsImxhc3RfbmFtZSI6InRhbWVyIn0.ls60Lt5ZHM_t7ngW1syX3eY5hxXFWXC1JFWFjyrqM8s",
									"type": "string"
								}
							]
						},
						"method": "GET",
						"header": [],
						"url": {
							"raw": "{{local}}/api/list_available_times?branch_id=1&date=2023-07-10",
							"host": [
								"{{local}}"
							],
							"path": [
								"api",
								"list_available_times"
							],
							"query": [
								{
									"key": "branch_id",
									"value": "1"
								},
								{
									"key": "date",
									"value": "2023-07-10"
								}
							]
						}
					},
					"response": [
						{
							"name": "List Slots",
							"originalRequest": {
								"method": "GET",
								"header": [],
								"url": {
									"raw": "{{local}}/api/list_available_times?branch_id=1&date=2023-07-10",
									"host": [
										"{{local}}"
									],
									"path": [
										"api",
										"list_available_times"
									],
									"query": [
										{
											"key": "branch_id",
											"value": "1"
										},
										{
											"key": "date",
											"value": "2023-07-10"
										}
									]
								}
							},
							"status": "OK",
							"code": 200,
							"_postman_previewlanguage": "json",
							"header": [
								{
									"key": "Date",
									"value": "Sun, 03 Dec 2023 10:02:42 GMT"
								},
								{
									"key": "Server",
									"value": "WSGIServer/0.2 CPython/3.10.8"
								},
								{
									"key": "Content-Type",
									"value": "application/json"
								},
								{
									"key": "Vary",
									"value": "Accept"
								},
								{
									"key": "Allow",
									"value": "GET, HEAD, OPTIONS"
								},
								{
									"key": "X-Frame-Options",
									"value": "DENY"
								},
								{
									"key": "Content-Length",
									"value": "475"
								},
								{
									"key": "X-Content-Type-Options",
									"value": "nosniff"
								},
								{
									"key": "Referrer-Policy",
									"value": "same-origin"
								}
							],
							"cookie": [],
							"body": "{\n    \"status\": true,\n    \"data\": [\n        {\n            \"id\": 4,\n            \"created_at\": \"2023-11-28T10:00:57.182045Z\",\n            \"updated_at\": \"2023-11-28T10:00:57.182045Z\",\n            \"time\": \"16:00:00\",\n            \"branch\": 1,\n            \"available\": true\n        },\n        {\n            \"id\": 3,\n            \"created_at\": \"2023-11-28T10:00:48.689560Z\",\n            \"updated_at\": \"2023-11-28T10:00:48.689560Z\",\n            \"time\": \"14:00:00\",\n            \"branch\": 1,\n            \"available\": true\n        },\n        {\n            \"id\": 2,\n            \"created_at\": \"2023-11-28T10:00:39.755515Z\",\n            \"updated_at\": \"2023-11-28T10:00:39.755515Z\",\n            \"time\": \"12:00:00\",\n            \"branch\": 1,\n            \"available\": true\n        }\n    ],\n    \"message\": \"تم بنجاح\"\n}"
						}
					]
				}
			]
		},
		{
			"name": "LookUps",
			"item": [
				{
					"name": "Car Model",
					"request": {
						"method": "GET",
						"header": [],
						"url": {
							"raw": "{{local}}/api/list_car_model",
							"host": [
								"{{local}}"
							],
							"path": [
								"api",
								"list_car_model"
							]
						}
					},
					"response": [
						{
							"name": "Car Model",
							"originalRequest": {
								"method": "GET",
								"header": [],
								"url": {
									"raw": "{{local}}/api/list_car_model",
									"host": [
										"{{local}}"
									],
									"path": [
										"api",
										"list_car_model"
									]
								}
							},
							"status": "OK",
							"code": 200,
							"_postman_previewlanguage": "json",
							"header": [
								{
									"key": "Date",
									"value": "Sun, 03 Dec 2023 09:44:54 GMT"
								},
								{
									"key": "Server",
									"value": "WSGIServer/0.2 CPython/3.10.8"
								},
								{
									"key": "Content-Type",
									"value": "application/json"
								},
								{
									"key": "Vary",
									"value": "Accept"
								},
								{
									"key": "Allow",
									"value": "GET, HEAD, OPTIONS"
								},
								{
									"key": "X-Frame-Options",
									"value": "DENY"
								},
								{
									"key": "Content-Length",
									"value": "228"
								},
								{
									"key": "X-Content-Type-Options",
									"value": "nosniff"
								},
								{
									"key": "Referrer-Policy",
									"value": "same-origin"
								}
							],
							"cookie": [],
							"body": "{\n    \"status\": true,\n    \"data\": [\n        {\n            \"id\": 1,\n            \"created_at\": \"2023-11-27T14:27:44.536256Z\",\n            \"updated_at\": \"2023-11-27T14:27:44.536256Z\",\n            \"car_model\": \"BMW\",\n            \"image\": \"/media/Users%20Cars/Screenshot_2023-10-18_122258.png\"\n        }\n    ],\n    \"message\": \"تم بنجاح\"\n}"
						}
					]
				},
				{
					"name": "list_branches",
					"request": {
						"method": "GET",
						"header": [],
						"url": {
							"raw": "{{local}}api/list_branches",
							"host": [
								"{{local}}api"
							],
							"path": [
								"list_branches"
							]
						}
					},
					"response": [
						{
							"name": "list_branches",
							"originalRequest": {
								"method": "GET",
								"header": [],
								"url": {
									"raw": "{{local}}/api/list_branches",
									"host": [
										"{{local}}"
									],
									"path": [
										"api",
										"list_branches"
									]
								}
							},
							"status": "OK",
							"code": 200,
							"_postman_previewlanguage": "json",
							"header": [
								{
									"key": "Date",
									"value": "Sun, 03 Dec 2023 09:45:10 GMT"
								},
								{
									"key": "Server",
									"value": "WSGIServer/0.2 CPython/3.10.8"
								},
								{
									"key": "Content-Type",
									"value": "application/json"
								},
								{
									"key": "Vary",
									"value": "Accept"
								},
								{
									"key": "Allow",
									"value": "GET, HEAD, OPTIONS"
								},
								{
									"key": "X-Frame-Options",
									"value": "DENY"
								},
								{
									"key": "Content-Length",
									"value": "488"
								},
								{
									"key": "X-Content-Type-Options",
									"value": "nosniff"
								},
								{
									"key": "Referrer-Policy",
									"value": "same-origin"
								}
							],
							"cookie": [],
							"body": "{\n    \"status\": true,\n    \"data\": [\n        {\n            \"id\": 2,\n            \"created_at\": \"2023-11-29T11:49:47.908609Z\",\n            \"updated_at\": \"2023-11-29T11:49:47.908609Z\",\n            \"name\": \"tagamo3\",\n            \"mobile1\": null,\n            \"mobile2\": null,\n            \"latitude\": \"34756428\",\n            \"langitude\": \"765475\",\n            \"address\": \"hcjhv,.\"\n        },\n        {\n            \"id\": 1,\n            \"created_at\": \"2023-11-29T11:27:03.526347Z\",\n            \"updated_at\": \"2023-11-29T11:27:03.526347Z\",\n            \"name\": \"maadi\",\n            \"mobile1\": 1099456302,\n            \"mobile2\": null,\n            \"latitude\": \"30393\",\n            \"langitude\": \"2323\",\n            \"address\": \"7 fahmy St Manyel el roodah ,cairo\"\n        }\n    ],\n    \"message\": \"تم بنجاح\"\n}"
						}
					]
				},
				{
					"name": "list_branches_slot",
					"request": {
						"method": "GET",
						"header": [],
						"url": {
							"raw": "{{local}}api/list_branches_slot",
							"host": [
								"{{local}}api"
							],
							"path": [
								"list_branches_slot"
							]
						}
					},
					"response": [
						{
							"name": "list_branches_slot",
							"originalRequest": {
								"method": "GET",
								"header": [],
								"url": {
									"raw": "{{local}}/api/list_branches_slot",
									"host": [
										"{{local}}"
									],
									"path": [
										"api",
										"list_branches_slot"
									]
								}
							},
							"status": "OK",
							"code": 200,
							"_postman_previewlanguage": "json",
							"header": [
								{
									"key": "Date",
									"value": "Sun, 03 Dec 2023 09:45:19 GMT"
								},
								{
									"key": "Server",
									"value": "WSGIServer/0.2 CPython/3.10.8"
								},
								{
									"key": "Content-Type",
									"value": "application/json"
								},
								{
									"key": "Vary",
									"value": "Accept"
								},
								{
									"key": "Allow",
									"value": "GET, HEAD, OPTIONS"
								},
								{
									"key": "X-Frame-Options",
									"value": "DENY"
								},
								{
									"key": "Content-Length",
									"value": "541"
								},
								{
									"key": "X-Content-Type-Options",
									"value": "nosniff"
								},
								{
									"key": "Referrer-Policy",
									"value": "same-origin"
								}
							],
							"cookie": [],
							"body": "{\n    \"status\": true,\n    \"data\": [\n        {\n            \"id\": 5,\n            \"created_at\": \"2023-11-29T11:50:00.735186Z\",\n            \"updated_at\": \"2023-11-29T11:50:00.735186Z\",\n            \"slot_number\": 11,\n            \"branch\": 2\n        },\n        {\n            \"id\": 4,\n            \"created_at\": \"2023-11-28T09:59:47.705664Z\",\n            \"updated_at\": \"2023-11-28T09:59:47.705664Z\",\n            \"slot_number\": 3,\n            \"branch\": 1\n        },\n        {\n            \"id\": 3,\n            \"created_at\": \"2023-11-28T09:59:43.517519Z\",\n            \"updated_at\": \"2023-11-28T09:59:43.517519Z\",\n            \"slot_number\": 2,\n            \"branch\": 1\n        },\n        {\n            \"id\": 2,\n            \"created_at\": \"2023-11-28T09:59:38.190296Z\",\n            \"updated_at\": \"2023-11-28T09:59:38.190296Z\",\n            \"slot_number\": 1,\n            \"branch\": 1\n        }\n    ],\n    \"message\": \"تم بنجاح\"\n}"
						}
					]
				},
				{
					"name": "ListServices",
					"request": {
						"method": "GET",
						"header": [],
						"url": {
							"raw": "{{local}}/api/list_services",
							"host": [
								"{{local}}"
							],
							"path": [
								"api",
								"list_services"
							]
						}
					},
					"response": [
						{
							"name": "ListServices",
							"originalRequest": {
								"method": "GET",
								"header": [],
								"url": {
									"raw": "{{local}}/api/list_services",
									"host": [
										"{{local}}"
									],
									"path": [
										"api",
										"list_services"
									]
								}
							},
							"status": "OK",
							"code": 200,
							"_postman_previewlanguage": "json",
							"header": [
								{
									"key": "Date",
									"value": "Sun, 03 Dec 2023 09:45:38 GMT"
								},
								{
									"key": "Server",
									"value": "WSGIServer/0.2 CPython/3.10.8"
								},
								{
									"key": "Content-Type",
									"value": "application/json"
								},
								{
									"key": "Vary",
									"value": "Accept"
								},
								{
									"key": "Allow",
									"value": "GET, HEAD, OPTIONS"
								},
								{
									"key": "X-Frame-Options",
									"value": "DENY"
								},
								{
									"key": "Content-Length",
									"value": "242"
								},
								{
									"key": "X-Content-Type-Options",
									"value": "nosniff"
								},
								{
									"key": "Referrer-Policy",
									"value": "same-origin"
								}
							],
							"cookie": [],
							"body": "{\n    \"status\": true,\n    \"data\": [\n        {\n            \"id\": 1,\n            \"created_at\": \"2023-11-27T19:12:12.617751Z\",\n            \"updated_at\": \"2023-11-27T19:12:12.617751Z\",\n            \"price\": 1500,\n            \"min_price\": 1000,\n            \"max_price\": 1500,\n            \"name\": \"test service\",\n            \"icons\": null,\n            \"points\": 100\n        }\n    ],\n    \"message\": \"تم بنجاح\"\n}"
						}
					]
				},
				{
					"name": "list_accessories",
					"request": {
						"method": "GET",
						"header": [],
						"url": {
							"raw": "{{local}}api/list_accessories",
							"host": [
								"{{local}}api"
							],
							"path": [
								"list_accessories"
							]
						}
					},
					"response": [
						{
							"name": "list_accessories",
							"originalRequest": {
								"method": "GET",
								"header": [],
								"url": {
									"raw": "{{local}}/api/list_accessories",
									"host": [
										"{{local}}"
									],
									"path": [
										"api",
										"list_accessories"
									]
								}
							},
							"status": "OK",
							"code": 200,
							"_postman_previewlanguage": "json",
							"header": [
								{
									"key": "Date",
									"value": "Sun, 03 Dec 2023 09:49:19 GMT"
								},
								{
									"key": "Server",
									"value": "WSGIServer/0.2 CPython/3.10.8"
								},
								{
									"key": "Content-Type",
									"value": "application/json"
								},
								{
									"key": "Vary",
									"value": "Accept"
								},
								{
									"key": "Allow",
									"value": "GET, HEAD, OPTIONS"
								},
								{
									"key": "X-Frame-Options",
									"value": "DENY"
								},
								{
									"key": "Content-Length",
									"value": "408"
								},
								{
									"key": "X-Content-Type-Options",
									"value": "nosniff"
								},
								{
									"key": "Referrer-Policy",
									"value": "same-origin"
								}
							],
							"cookie": [],
							"body": "{\n    \"status\": true,\n    \"data\": [\n        {\n            \"id\": 2,\n            \"compatible_with\": [\n                {\n                    \"id\": 1,\n                    \"created_at\": \"2023-11-27T14:27:44.536256Z\",\n                    \"updated_at\": \"2023-11-27T14:27:44.536256Z\",\n                    \"car_model\": \"BMW\",\n                    \"image\": \"/media/Users%20Cars/Screenshot_2023-10-18_122258.png\"\n                }\n            ],\n            \"created_at\": \"2023-12-03T09:49:16.192689Z\",\n            \"updated_at\": \"2023-12-03T09:49:16.192689Z\",\n            \"title\": \"access\",\n            \"about\": \"test about\",\n            \"price\": 10000,\n            \"discount\": 0\n        }\n    ],\n    \"message\": \"تم بنجاح\"\n}"
						}
					]
				},
				{
					"name": "list_offers",
					"request": {
						"method": "GET",
						"header": [],
						"url": {
							"raw": "{{local}}/api/list_offers",
							"host": [
								"{{local}}"
							],
							"path": [
								"api",
								"list_offers"
							]
						}
					},
					"response": [
						{
							"name": "list_offers",
							"originalRequest": {
								"method": "GET",
								"header": [],
								"url": {
									"raw": "{{local}}/api/list_offers",
									"host": [
										"{{local}}"
									],
									"path": [
										"api",
										"list_offers"
									]
								}
							},
							"status": "OK",
							"code": 200,
							"_postman_previewlanguage": "json",
							"header": [
								{
									"key": "Date",
									"value": "Sun, 03 Dec 2023 09:49:33 GMT"
								},
								{
									"key": "Server",
									"value": "WSGIServer/0.2 CPython/3.10.8"
								},
								{
									"key": "Content-Type",
									"value": "application/json"
								},
								{
									"key": "Vary",
									"value": "Accept"
								},
								{
									"key": "Allow",
									"value": "GET, HEAD, OPTIONS"
								},
								{
									"key": "X-Frame-Options",
									"value": "DENY"
								},
								{
									"key": "Content-Length",
									"value": "424"
								},
								{
									"key": "X-Content-Type-Options",
									"value": "nosniff"
								},
								{
									"key": "Referrer-Policy",
									"value": "same-origin"
								}
							],
							"cookie": [],
							"body": "{\n    \"status\": true,\n    \"data\": [\n        {\n            \"id\": 1,\n            \"compatible_with\": [\n                {\n                    \"id\": 1,\n                    \"created_at\": \"2023-11-27T14:27:44.536256Z\",\n                    \"updated_at\": \"2023-11-27T14:27:44.536256Z\",\n                    \"car_model\": \"BMW\",\n                    \"image\": \"/media/Users%20Cars/Screenshot_2023-10-18_122258.png\"\n                }\n            ],\n            \"created_at\": \"2023-11-27T14:50:06.143883Z\",\n            \"updated_at\": \"2023-11-27T14:59:08.174918Z\",\n            \"title\": \"test\",\n            \"about\": \"sfdcghjkl;\",\n            \"price\": 100,\n            \"discount\": 20,\n            \"price_after\": 80\n        }\n    ],\n    \"message\": \"تم بنجاح\"\n}"
						}
					]
				},
				{
					"name": "ListUsedCars",
					"request": {
						"method": "GET",
						"header": [],
						"url": {
							"raw": "{{local}}api/list_used_cars",
							"host": [
								"{{local}}api"
							],
							"path": [
								"list_used_cars"
							]
						}
					},
					"response": [
						{
							"name": "ListUsedCars",
							"originalRequest": {
								"method": "GET",
								"header": [],
								"url": {
									"raw": "{{local}}/api/list_used_cars",
									"host": [
										"{{local}}"
									],
									"path": [
										"api",
										"list_used_cars"
									]
								}
							},
							"status": "OK",
							"code": 200,
							"_postman_previewlanguage": "json",
							"header": [
								{
									"key": "Date",
									"value": "Sun, 03 Dec 2023 09:49:49 GMT"
								},
								{
									"key": "Server",
									"value": "WSGIServer/0.2 CPython/3.10.8"
								},
								{
									"key": "Content-Type",
									"value": "application/json"
								},
								{
									"key": "Vary",
									"value": "Accept"
								},
								{
									"key": "Allow",
									"value": "GET, HEAD, OPTIONS"
								},
								{
									"key": "X-Frame-Options",
									"value": "DENY"
								},
								{
									"key": "Content-Length",
									"value": "258"
								},
								{
									"key": "X-Content-Type-Options",
									"value": "nosniff"
								},
								{
									"key": "Referrer-Policy",
									"value": "same-origin"
								}
							],
							"cookie": [],
							"body": "{\n    \"status\": true,\n    \"data\": [\n        {\n            \"id\": 1,\n            \"created_at\": \"2023-11-27T14:42:14.791777Z\",\n            \"updated_at\": \"2023-11-27T14:42:14.791777Z\",\n            \"title\": \"test\",\n            \"description\": \"dfsghjkl/.kjhgfdsfghmj,k.\",\n            \"price\": 15000000,\n            \"car_model\": 1,\n            \"branch\": 1,\n            \"images\": []\n        }\n    ],\n    \"message\": \"تم بنجاح\"\n}"
						}
					]
				},
				{
					"name": "Loyalty Level",
					"request": {
						"auth": {
							"type": "bearer",
							"bearer": [
								{
									"key": "token",
									"value": "eyJ0eXAiOiJKV1QiLCJhbGciOiJIUzI1NiJ9.eyJ0b2tlbl90eXBlIjoiYWNjZXNzIiwiZXhwIjoxNzA4ODcxMTkzLCJqdGkiOiJiNGEzMWNhYTQxNzM0NjY5ODVhNGU0OTRlYWUyZDQ1YSIsInVzZXJfaWQiOiIzIiwiZmlyc3RfbmFtZSI6Inlhc3NlbiIsImxhc3RfbmFtZSI6InRhbWVyIn0.ls60Lt5ZHM_t7ngW1syX3eY5hxXFWXC1JFWFjyrqM8s",
									"type": "string"
								}
							]
						},
						"method": "GET",
						"header": [],
						"url": {
							"raw": "{{local}}/api/loyalty_level",
							"host": [
								"{{local}}"
							],
							"path": [
								"api",
								"loyalty_level"
							]
						}
					},
					"response": [
						{
							"name": "Loyalty Level",
							"originalRequest": {
								"method": "GET",
								"header": [],
								"url": {
									"raw": "{{local}}/api/loyalty_level",
									"host": [
										"{{local}}"
									],
									"path": [
										"api",
										"loyalty_level"
									]
								}
							},
							"status": "OK",
							"code": 200,
							"_postman_previewlanguage": "json",
							"header": [
								{
									"key": "Date",
									"value": "Sun, 03 Dec 2023 09:50:21 GMT"
								},
								{
									"key": "Server",
									"value": "WSGIServer/0.2 CPython/3.10.8"
								},
								{
									"key": "Content-Type",
									"value": "application/json"
								},
								{
									"key": "Vary",
									"value": "Accept"
								},
								{
									"key": "Allow",
									"value": "GET, HEAD, OPTIONS"
								},
								{
									"key": "X-Frame-Options",
									"value": "DENY"
								},
								{
									"key": "Content-Length",
									"value": "175"
								},
								{
									"key": "X-Content-Type-Options",
									"value": "nosniff"
								},
								{
									"key": "Referrer-Policy",
									"value": "same-origin"
								}
							],
							"cookie": [],
							"body": "{\n    \"status\": true,\n    \"data\": [\n        {\n            \"id\": 1,\n            \"created_at\": \"2023-12-03T09:50:18.690574Z\",\n            \"updated_at\": \"2023-12-03T09:50:18.690574Z\",\n            \"type\": \"bronze\",\n            \"point\": 400\n        }\n    ],\n    \"message\": \"تم بنجاح\"\n}"
						}
					]
				}
			]
		},
		{
			"name": "other",
			"item": [
				{
					"name": "maintenance_schedule",
					"request": {
						"method": "GET",
						"header": [],
						"url": {
							"raw": "{{local}}/api/maintenance_schedule",
							"host": [
								"{{local}}"
							],
							"path": [
								"api",
								"maintenance_schedule"
							]
						}
					},
					"response": [
						{
							"name": "maintenance_schedule",
							"originalRequest": {
								"method": "GET",
								"header": [],
								"url": {
									"raw": "{{local}}/api/maintenance_schedule",
									"host": [
										"{{local}}"
									],
									"path": [
										"api",
										"maintenance_schedule"
									]
								}
							},
							"status": "OK",
							"code": 200,
							"_postman_previewlanguage": "json",
							"header": [
								{
									"key": "Date",
									"value": "Sun, 03 Dec 2023 09:51:53 GMT"
								},
								{
									"key": "Server",
									"value": "WSGIServer/0.2 CPython/3.10.8"
								},
								{
									"key": "Content-Type",
									"value": "application/json"
								},
								{
									"key": "Vary",
									"value": "Accept"
								},
								{
									"key": "Allow",
									"value": "GET, HEAD, OPTIONS"
								},
								{
									"key": "X-Frame-Options",
									"value": "DENY"
								},
								{
									"key": "Content-Length",
									"value": "225"
								},
								{
									"key": "X-Content-Type-Options",
									"value": "nosniff"
								},
								{
									"key": "Referrer-Policy",
									"value": "same-origin"
								}
							],
							"cookie": [],
							"body": "{\n    \"status\": true,\n    \"data\": [\n        {\n            \"id\": 1,\n            \"created_at\": \"2023-12-03T09:51:49.915110Z\",\n            \"updated_at\": \"2023-12-03T09:51:49.915110Z\",\n            \"description\": \"hdgsfhjklhgfdsasflkj;kjfsdxcvb nm,l;oiurxbn mkliuythfgxcvb ,m\"\n        }\n    ],\n    \"message\": \"تم بنجاح\"\n}"
						}
					]
				},
				{
					"name": "About Us",
					"request": {
						"method": "GET",
						"header": [],
						"url": {
							"raw": "{{local}}/api/list_aboutus",
							"host": [
								"{{local}}"
							],
							"path": [
								"api",
								"list_aboutus"
							]
						}
					},
					"response": [
						{
							"name": "About Us",
							"originalRequest": {
								"method": "GET",
								"header": [],
								"url": {
									"raw": "{{local}}/api/list_aboutus",
									"host": [
										"{{local}}"
									],
									"path": [
										"api",
										"list_aboutus"
									]
								}
							},
							"status": "OK",
							"code": 200,
							"_postman_previewlanguage": "json",
							"header": [
								{
									"key": "Date",
									"value": "Sun, 03 Dec 2023 09:52:39 GMT"
								},
								{
									"key": "Server",
									"value": "WSGIServer/0.2 CPython/3.10.8"
								},
								{
									"key": "Content-Type",
									"value": "application/json"
								},
								{
									"key": "Vary",
									"value": "Accept"
								},
								{
									"key": "Allow",
									"value": "GET, HEAD, OPTIONS"
								},
								{
									"key": "X-Frame-Options",
									"value": "DENY"
								},
								{
									"key": "Content-Length",
									"value": "207"
								},
								{
									"key": "X-Content-Type-Options",
									"value": "nosniff"
								},
								{
									"key": "Referrer-Policy",
									"value": "same-origin"
								}
							],
							"cookie": [],
							"body": "{\n    \"status\": true,\n    \"data\": [\n        {\n            \"id\": 1,\n            \"created_at\": \"2023-12-03T09:52:35.315290Z\",\n            \"updated_at\": \"2023-12-03T09:52:35.315290Z\",\n            \"about\": \"dajkdshgfkjABSCkjhGSAdxgsoianxdZIGASDXgoizdgqoisg\"\n        }\n    ],\n    \"message\": \"تم بنجاح\"\n}"
						}
					]
				},
				{
					"name": "FeedBack",
					"request": {
						"method": "POST",
						"header": [],
						"body": {
							"mode": "raw",
							"raw": "{\r\n    \"car_model\":1,\r\n    \"fullname\":\"yassen\",\r\n    \"email\":\"test@test.com\",\r\n    \"phone_number\":\"01099456302\",\r\n    \"feedback_subject\":\"yeyshsgdgdg\",\r\n    \"feedback_details\":\"kjdhnmkiuyfvn\"\r\n}",
							"options": {
								"raw": {
									"language": "json"
								}
							}
						},
						"url": {
							"raw": "{{local}}/api/feedback",
							"host": [
								"{{local}}"
							],
							"path": [
								"api",
								"feedback"
							]
						}
					},
					"response": [
						{
							"name": "FeedBack",
							"originalRequest": {
								"method": "POST",
								"header": [],
								"body": {
									"mode": "raw",
									"raw": "{\r\n    \"car_model\":1,\r\n    \"fullname\":\"yassen\",\r\n    \"email\":\"test@test.com\",\r\n    \"phone_number\":\"01099456302\",\r\n    \"feedback_subject\":\"yeyshsgdgdg\",\r\n    \"feedback_details\":\"kjdhnmkiuyfvn\"\r\n}",
									"options": {
										"raw": {
											"language": "json"
										}
									}
								},
								"url": {
									"raw": "{{local}}/api/feedback",
									"host": [
										"{{local}}"
									],
									"path": [
										"api",
										"feedback"
									]
								}
							},
							"status": "OK",
							"code": 200,
							"_postman_previewlanguage": "json",
							"header": [
								{
									"key": "Date",
									"value": "Sun, 03 Dec 2023 10:02:07 GMT"
								},
								{
									"key": "Server",
									"value": "WSGIServer/0.2 CPython/3.10.8"
								},
								{
									"key": "Content-Type",
									"value": "application/json"
								},
								{
									"key": "Vary",
									"value": "Accept"
								},
								{
									"key": "Allow",
									"value": "POST, OPTIONS"
								},
								{
									"key": "X-Frame-Options",
									"value": "DENY"
								},
								{
									"key": "Content-Length",
									"value": "300"
								},
								{
									"key": "X-Content-Type-Options",
									"value": "nosniff"
								},
								{
									"key": "Referrer-Policy",
									"value": "same-origin"
								}
							],
							"cookie": [],
							"body": "{\n    \"status\": true,\n    \"data\": {\n        \"id\": 2,\n        \"created_at\": \"2023-12-03T10:02:07.741676Z\",\n        \"updated_at\": \"2023-12-03T10:02:07.741676Z\",\n        \"fullname\": \"yassen\",\n        \"email\": \"test@test.com\",\n        \"phone_number\": \"01099456302\",\n        \"feedback_subject\": \"yeyshsgdgdg\",\n        \"feedback_details\": \"kjdhnmkiuyfvn\",\n        \"car_model\": 1\n    },\n    \"message\": \"تم بنجاح\"\n}"
						}
					]
				},
				{
					"name": "Contact Us",
					"request": {
						"method": "POST",
						"header": [],
						"body": {
							"mode": "raw",
							"raw": "{\r\n    \"car_model\":1,\r\n    \"fullname\":\"yassen\",\r\n    \"email\":\"test@test.com\",\r\n    \"phone_number\":\"01099456302\",\r\n    \"inquiry_details\":\"kjdhnmkiuyfvn\"\r\n}",
							"options": {
								"raw": {
									"language": "json"
								}
							}
						},
						"url": {
							"raw": "{{local}}/api/contact_us",
							"host": [
								"{{local}}"
							],
							"path": [
								"api",
								"contact_us"
							]
						}
					},
					"response": [
						{
							"name": "Contact Us",
							"originalRequest": {
								"method": "POST",
								"header": [],
								"body": {
									"mode": "raw",
									"raw": "{\r\n    \"car_model\":1,\r\n    \"fullname\":\"yassen\",\r\n    \"email\":\"test@test.com\",\r\n    \"phone_number\":\"01099456302\",\r\n    \"inquiry_details\":\"kjdhnmkiuyfvn\"\r\n}",
									"options": {
										"raw": {
											"language": "json"
										}
									}
								},
								"url": {
									"raw": "{{local}}/api/contact_us",
									"host": [
										"{{local}}"
									],
									"path": [
										"api",
										"contact_us"
									]
								}
							},
							"status": "OK",
							"code": 200,
							"_postman_previewlanguage": "json",
							"header": [
								{
									"key": "Date",
									"value": "Sun, 03 Dec 2023 10:02:18 GMT"
								},
								{
									"key": "Server",
									"value": "WSGIServer/0.2 CPython/3.10.8"
								},
								{
									"key": "Content-Type",
									"value": "application/json"
								},
								{
									"key": "Vary",
									"value": "Accept"
								},
								{
									"key": "Allow",
									"value": "POST, OPTIONS"
								},
								{
									"key": "X-Frame-Options",
									"value": "DENY"
								},
								{
									"key": "Content-Length",
									"value": "266"
								},
								{
									"key": "X-Content-Type-Options",
									"value": "nosniff"
								},
								{
									"key": "Referrer-Policy",
									"value": "same-origin"
								}
							],
							"cookie": [],
							"body": "{\n    \"status\": true,\n    \"data\": {\n        \"id\": 2,\n        \"created_at\": \"2023-12-03T10:02:18.068292Z\",\n        \"updated_at\": \"2023-12-03T10:02:18.068292Z\",\n        \"fullname\": \"yassen\",\n        \"email\": \"test@test.com\",\n        \"phone_number\": \"01099456302\",\n        \"inquiry_details\": \"kjdhnmkiuyfvn\",\n        \"car_model\": 1\n    },\n    \"message\": \"تم بنجاح\"\n}"
						}
					]
				},
				{
					"name": "Create Technical Assistant",
					"request": {
						"auth": {
							"type": "bearer",
							"bearer": [
								{
									"key": "token",
									"value": "eyJ0eXAiOiJKV1QiLCJhbGciOiJIUzI1NiJ9.eyJ0b2tlbl90eXBlIjoiYWNjZXNzIiwiZXhwIjoxNzA4OTQ4ODMyLCJqdGkiOiI0Yjk3ZWY5MmNiMmM0YmVmOThiODE4OTM1ZWU5MDY2ZSIsInVzZXJfaWQiOiIzIiwiZmlyc3RfbmFtZSI6Inlhc3NlbiIsImxhc3RfbmFtZSI6InRhbWVyIn0.P_C2NpTaqQPKCroSIcfFxbU6jSGZegSKH8ZSYXk2F9s",
									"type": "string"
								}
							]
						},
						"method": "POST",
						"header": [
							{
								"key": "Authorization",
								"value": "token  eyJ0eXAiOiJKV1QiLCJhbGciOiJIUzI1NiJ9.eyJ0b2tlbl90eXBlIjoiYWNjZXNzIiwiZXhwIjoxNzA4OTQ4ODMyLCJqdGkiOiI0Yjk3ZWY5MmNiMmM0YmVmOThiODE4OTM1ZWU5MDY2ZSIsInVzZXJfaWQiOiIzIiwiZmlyc3RfbmFtZSI6Inlhc3NlbiIsImxhc3RfbmFtZSI6InRhbWVyIn0.P_C2NpTaqQPKCroSIcfFxbU6jSGZegSKH8ZSYXk2F9s\",\n",
								"type": "text",
								"disabled": true
							}
						],
						"body": {
							"mode": "raw",
							"raw": "{\r\n    \"question\":\"i need a question \"\r\n\r\n}",
							"options": {
								"raw": {
									"language": "json"
								}
							}
						},
						"url": {
							"raw": "{{local}}/api/create_technical_assistant",
							"host": [
								"{{local}}"
							],
							"path": [
								"api",
								"create_technical_assistant"
							]
						}
					},
					"response": [
						{
							"name": "Create Technical Assistant",
							"originalRequest": {
								"method": "POST",
								"header": [
									{
										"key": "Authorization",
										"value": "token  eyJ0eXAiOiJKV1QiLCJhbGciOiJIUzI1NiJ9.eyJ0b2tlbl90eXBlIjoiYWNjZXNzIiwiZXhwIjoxNzA4OTQ4ODMyLCJqdGkiOiI0Yjk3ZWY5MmNiMmM0YmVmOThiODE4OTM1ZWU5MDY2ZSIsInVzZXJfaWQiOiIzIiwiZmlyc3RfbmFtZSI6Inlhc3NlbiIsImxhc3RfbmFtZSI6InRhbWVyIn0.P_C2NpTaqQPKCroSIcfFxbU6jSGZegSKH8ZSYXk2F9s\",\n",
										"type": "text",
										"disabled": true
									}
								],
								"body": {
									"mode": "raw",
									"raw": "{\r\n    \"question\":\"i need a question \"\r\n\r\n}",
									"options": {
										"raw": {
											"language": "json"
										}
									}
								},
								"url": {
									"raw": "{{local}}/api/create_technical_assistant",
									"host": [
										"{{local}}"
									],
									"path": [
										"api",
										"create_technical_assistant"
									]
								}
							},
							"status": "Created",
							"code": 201,
							"_postman_previewlanguage": "json",
							"header": [
								{
									"key": "Date",
									"value": "Sun, 03 Dec 2023 09:53:02 GMT"
								},
								{
									"key": "Server",
									"value": "WSGIServer/0.2 CPython/3.10.8"
								},
								{
									"key": "Content-Type",
									"value": "application/json"
								},
								{
									"key": "Vary",
									"value": "Accept"
								},
								{
									"key": "Allow",
									"value": "POST, OPTIONS"
								},
								{
									"key": "X-Frame-Options",
									"value": "DENY"
								},
								{
									"key": "Content-Length",
									"value": "74"
								},
								{
									"key": "X-Content-Type-Options",
									"value": "nosniff"
								},
								{
									"key": "Referrer-Policy",
									"value": "same-origin"
								}
							],
							"cookie": [],
							"body": "{\n    \"status\": true,\n    \"data\": \"submited successfully\",\n    \"message\": \"تم بنجاح\"\n}"
						}
					]
				},
				{
					"name": "List Technical Assistant",
					"request": {
						"auth": {
							"type": "bearer",
							"bearer": [
								{
									"key": "token",
									"value": "eyJ0eXAiOiJKV1QiLCJhbGciOiJIUzI1NiJ9.eyJ0b2tlbl90eXBlIjoiYWNjZXNzIiwiZXhwIjoxNzA4OTQ4ODMyLCJqdGkiOiI0Yjk3ZWY5MmNiMmM0YmVmOThiODE4OTM1ZWU5MDY2ZSIsInVzZXJfaWQiOiIzIiwiZmlyc3RfbmFtZSI6Inlhc3NlbiIsImxhc3RfbmFtZSI6InRhbWVyIn0.P_C2NpTaqQPKCroSIcfFxbU6jSGZegSKH8ZSYXk2F9s",
									"type": "string"
								}
							]
						},
						"method": "GET",
						"header": [],
						"url": {
							"raw": "{{local}}/api/list_technical_assistant",
							"host": [
								"{{local}}"
							],
							"path": [
								"api",
								"list_technical_assistant"
							]
						}
					},
					"response": [
						{
							"name": "List Technical Assistant",
							"originalRequest": {
								"method": "GET",
								"header": [],
								"url": {
									"raw": "{{local}}/api/list_technical_assistant",
									"host": [
										"{{local}}"
									],
									"path": [
										"api",
										"list_technical_assistant"
									]
								}
							},
							"status": "OK",
							"code": 200,
							"_postman_previewlanguage": "json",
							"header": [
								{
									"key": "Date",
									"value": "Sun, 03 Dec 2023 09:52:51 GMT"
								},
								{
									"key": "Server",
									"value": "WSGIServer/0.2 CPython/3.10.8"
								},
								{
									"key": "Content-Type",
									"value": "application/json"
								},
								{
									"key": "Vary",
									"value": "Accept"
								},
								{
									"key": "Allow",
									"value": "GET, HEAD, OPTIONS"
								},
								{
									"key": "X-Frame-Options",
									"value": "DENY"
								},
								{
									"key": "Content-Length",
									"value": "538"
								},
								{
									"key": "X-Content-Type-Options",
									"value": "nosniff"
								},
								{
									"key": "Referrer-Policy",
									"value": "same-origin"
								}
							],
							"cookie": [],
							"body": "{\n    \"status\": true,\n    \"data\": [\n        {\n            \"id\": 4,\n            \"created_at\": \"2023-11-28T12:03:10.931527Z\",\n            \"updated_at\": \"2023-11-28T12:03:10.931527Z\",\n            \"question\": \"i need a question\",\n            \"answer\": null,\n            \"read\": false,\n            \"user\": 3\n        },\n        {\n            \"id\": 3,\n            \"created_at\": \"2023-11-28T12:02:59.085903Z\",\n            \"updated_at\": \"2023-11-28T12:02:59.085903Z\",\n            \"question\": \"i need a question\",\n            \"answer\": null,\n            \"read\": false,\n            \"user\": 3\n        },\n        {\n            \"id\": 2,\n            \"created_at\": \"2023-11-28T12:01:58.790587Z\",\n            \"updated_at\": \"2023-11-28T12:01:58.790587Z\",\n            \"question\": \"i need a question\",\n            \"answer\": null,\n            \"read\": false,\n            \"user\": 3\n        }\n    ],\n    \"message\": \"تم بنجاح\"\n}"
						}
					]
				},
				{
					"name": "Redeem Points",
					"request": {
						"auth": {
							"type": "bearer",
							"bearer": [
								{
									"key": "token",
									"value": "eyJ0eXAiOiJKV1QiLCJhbGciOiJIUzI1NiJ9.eyJ0b2tlbl90eXBlIjoiYWNjZXNzIiwiZXhwIjoxNzEwNDMxMTcyLCJqdGkiOiI5YTEyYzg1Mjk0YzA0MDhhYTcyYTEzY2RlZWM1ZWIxMyIsInVzZXJfaWQiOiIzIiwiZmlyc3RfbmFtZSI6Inlhc3NlbiIsImxhc3RfbmFtZSI6InRhbWVyIn0.2Z5aaLBkPuWzzeTtTYbSuTWNGrLxqBORZdwhrcCuLZc",
									"type": "string"
								}
							]
						},
						"method": "POST",
						"header": [],
						"body": {
							"mode": "raw",
							"raw": "{\r\n    \"service_id\":1,\r\n    \"price\":1000\r\n}",
							"options": {
								"raw": {
									"language": "json"
								}
							}
						},
						"url": {
							"raw": "{{local}}/api/redeem_points",
							"host": [
								"{{local}}"
							],
							"path": [
								"api",
								"redeem_points"
							]
						}
					},
					"response": []
				}
			]
		},
		{
			"name": "Road Map Assistant",
			"request": {
				"auth": {
					"type": "bearer",
					"bearer": [
						{
							"key": "token",
							"value": "eyJ0eXAiOiJKV1QiLCJhbGciOiJIUzI1NiJ9.eyJ0b2tlbl90eXBlIjoiYWNjZXNzIiwiZXhwIjoxNzA4OTQ4ODMyLCJqdGkiOiI0Yjk3ZWY5MmNiMmM0YmVmOThiODE4OTM1ZWU5MDY2ZSIsInVzZXJfaWQiOiIzIiwiZmlyc3RfbmFtZSI6Inlhc3NlbiIsImxhc3RfbmFtZSI6InRhbWVyIn0.P_C2NpTaqQPKCroSIcfFxbU6jSGZegSKH8ZSYXk2F9s",
							"type": "string"
						}
					]
				},
				"method": "POST",
				"header": [],
				"body": {
					"mode": "raw",
					"raw": "{\r\n    \"langtiude\":\"3.27252\",\r\n    \"latitude\":\"2.83673\",\r\n    \"car\":1\r\n}",
					"options": {
						"raw": {
							"language": "json"
						}
					}
				},
				"url": {
					"raw": "{{local}}/api/road_help",
					"host": [
						"{{local}}"
					],
					"path": [
						"api",
						"road_help"
					]
				}
			},
			"response": [
				{
					"name": "Road Map Assistant",
					"originalRequest": {
						"method": "POST",
						"header": [],
						"body": {
							"mode": "raw",
							"raw": "{\r\n    \"langtiude\":\"3.27252\",\r\n    \"latitude\":\"2.83673\",\r\n    \"car\":1\r\n}",
							"options": {
								"raw": {
									"language": "json"
								}
							}
						},
						"url": {
							"raw": "{{local}}/api/road_help",
							"host": [
								"{{local}}"
							],
							"path": [
								"api",
								"road_help"
							]
						}
					},
					"status": "OK",
					"code": 200,
					"_postman_previewlanguage": "json",
					"header": [
						{
							"key": "Date",
							"value": "Sun, 03 Dec 2023 09:50:33 GMT"
						},
						{
							"key": "Server",
							"value": "WSGIServer/0.2 CPython/3.10.8"
						},
						{
							"key": "Content-Type",
							"value": "application/json"
						},
						{
							"key": "Vary",
							"value": "Accept"
						},
						{
							"key": "Allow",
							"value": "POST, OPTIONS"
						},
						{
							"key": "X-Frame-Options",
							"value": "DENY"
						},
						{
							"key": "Content-Length",
							"value": "219"
						},
						{
							"key": "X-Content-Type-Options",
							"value": "nosniff"
						},
						{
							"key": "Referrer-Policy",
							"value": "same-origin"
						}
					],
					"cookie": [],
					"body": "{\n    \"status\": true,\n    \"data\": {\n        \"id\": 4,\n        \"created_at\": \"2023-12-03T09:50:33.886155Z\",\n        \"updated_at\": \"2023-12-03T09:50:33.886155Z\",\n        \"langtiude\": \"3.27252\",\n        \"latitude\": \"2.83673\",\n        \"valid\": false,\n        \"user\": 3,\n        \"car\": 1\n    },\n    \"message\": \"تم بنجاح\"\n}"
				},
				{
					"name": "Road Map Assistant",
					"originalRequest": {
						"method": "POST",
						"header": [],
						"body": {
							"mode": "raw",
							"raw": "{\r\n    \"langtiude\": \"3.27252\",\r\n    \"latitude\": \"2.83673\",\r\n    \"car\": 6\r\n}",
							"options": {
								"raw": {
									"language": "json"
								}
							}
						},
						"url": {
							"raw": "{{local}}/api/road_help",
							"host": [
								"{{local}}"
							],
							"path": [
								"api",
								"road_help"
							]
						}
					},
					"status": "Bad Request",
					"code": 400,
					"_postman_previewlanguage": "json",
					"header": [
						{
							"key": "Date",
							"value": "Sun, 03 Dec 2023 09:50:46 GMT"
						},
						{
							"key": "Server",
							"value": "WSGIServer/0.2 CPython/3.10.8"
						},
						{
							"key": "Content-Type",
							"value": "application/json"
						},
						{
							"key": "Vary",
							"value": "Accept"
						},
						{
							"key": "Allow",
							"value": "POST, OPTIONS"
						},
						{
							"key": "X-Frame-Options",
							"value": "DENY"
						},
						{
							"key": "Content-Length",
							"value": "53"
						},
						{
							"key": "X-Content-Type-Options",
							"value": "nosniff"
						},
						{
							"key": "Referrer-Policy",
							"value": "same-origin"
						}
					],
					"cookie": [],
					"body": "{\n    \"car\": [\n        \"Invalid pk \\\"6\\\" - object does not exist.\"\n    ]\n}"
				}
			]
		},
		{
			"name": "http://127.0.0.1:8000/api/upload",
			"request": {
				"auth": {
					"type": "noauth"
				},
				"method": "POST",
				"header": [],
				"body": {
					"mode": "formdata",
					"formdata": [
						{
							"key": "files",
							"type": "file",
							"src": [
								"/D:/Level 2/summer 2018/Selected topics/DS&PR_Lec1.pdf",
								"/D:/Level 2/designpatterns-online.pdf"
							]
						}
					]
				},
				"url": {
					"raw": "http://127.0.0.1:8000/api/upload",
					"protocol": "http",
					"host": [
						"127",
						"0",
						"0",
						"1"
					],
					"port": "8000",
					"path": [
						"api",
						"upload"
					]
				}
			},
			"response": []
		}
	]
}